sparc.requests-1.0.2-py2.7-nspkg.pth
sparc/requests/__init__.py
sparc/requests/configure.zcml
sparc/requests/ftesting.zcml
sparc/requests/interfaces.py
sparc/requests/request.py
sparc/requests/testing.py
sparc/requests/tests/__init__.py
sparc/requests/tests/test_request.py
sparc.requests-1.0.2.dist-info/DESCRIPTION.rst
sparc.requests-1.0.2.dist-info/METADATA
sparc.requests-1.0.2.dist-info/RECORD
sparc.requests-1.0.2.dist-info/WHEEL
sparc.requests-1.0.2.dist-info/entry_points.txt
sparc.requests-1.0.2.dist-info/metadata.json
sparc.requests-1.0.2.dist-info/namespace_packages.txt
sparc.requests-1.0.2.dist-info/top_level.txt
